{"_default": {"11": {"startTime": "Monday May, 11 2020 16:28:05", "duration": 571.9, "avSpeed": 75.64, "avRPM": 73.0, "avEngineLoad": 48.35, "avCoolantTemp": 48.13, "avThrottlePos": 49.47, "nSnaps": 144, "snaps": [{"speed": 0, "rpm": 0, "engineLoad": 0, "coolantTemp": 0, "throttlePos": 0, "startTime": 1589203685.9873104, "steps": 0}, {"speed": 89.2, "rpm": 53.8, "engineLoad": 42.8, "coolantTemp": 40.4, "throttlePos": 63.2, "startTime": 1589203686.0162327, "steps": 5}, {"speed": 81.0, "rpm": 67.5, "engineLoad": 40.25, "coolantTemp": 61.25, "throttlePos": 67.5, "startTime": 1589203689.9665248, "steps": 4}, {"speed": 86.5, "rpm": 50.75, "engineLoad": 50.25, "coolantTemp": 60.0, "throttlePos": 65.25, "startTime": 1589203693.969533, "steps": 4}, {"speed": 69.0, "rpm": 90.75, "engineLoad": 31.25, "coolantTemp": 18.5, "throttlePos": 47.0, "startTime": 1589203697.966309, "steps": 4}, {"speed": 59.75, "rpm": 70.25, "engineLoad": 63.75, "coolantTemp": 69.5, "throttlePos": 66.75, "startTime": 1589203701.9693377, "steps": 4}, {"speed": 82.0, "rpm": 104.75, "engineLoad": 30.75, "coolantTemp": 33.5, "throttlePos": 40.75, "startTime": 1589203705.9724746, "steps": 4}, {"speed": 95.0, "rpm": 63.0, "engineLoad": 33.75, "coolantTemp": 33.0, "throttlePos": 34.25, "startTime": 1589203709.9671593, "steps": 4}, {"speed": 101.0, "rpm": 76.5, "engineLoad": 72.0, "coolantTemp": 37.5, "throttlePos": 27.5, "startTime": 1589203713.970119, "steps": 4}, {"speed": 93.5, "rpm": 55.25, "engineLoad": 12.5, "coolantTemp": 33.5, "throttlePos": 43.5, "startTime": 1589203717.970459, "steps": 4}, {"speed": 64.75, "rpm": 88.5, "engineLoad": 33.0, "coolantTemp": 53.0, "throttlePos": 28.0, "startTime": 1589203721.9675684, "steps": 4}, {"speed": 32.0, "rpm": 90.25, "engineLoad": 49.75, "coolantTemp": 32.25, "throttlePos": 41.5, "startTime": 1589203725.9665332, "steps": 4}, {"speed": 67.5, "rpm": 43.25, "engineLoad": 42.0, "coolantTemp": 23.0, "throttlePos": 42.5, "startTime": 1589203729.968357, "steps": 4}, {"speed": 25.25, "rpm": 95.0, "engineLoad": 45.5, "coolantTemp": 18.75, "throttlePos": 28.5, "startTime": 1589203733.966586, "steps": 4}, {"speed": 95.5, "rpm": 104.5, "engineLoad": 17.0, "coolantTemp": 71.75, "throttlePos": 53.5, "startTime": 1589203737.9685292, "steps": 4}, {"speed": 50.5, "rpm": 112.75, "engineLoad": 60.25, "coolantTemp": 29.25, "throttlePos": 62.75, "startTime": 1589203741.9682372, "steps": 4}, {"speed": 88.75, "rpm": 70.25, "engineLoad": 64.5, "coolantTemp": 51.5, "throttlePos": 41.0, "startTime": 1589203745.965868, "steps": 4}, {"speed": 49.0, "rpm": 108.75, "engineLoad": 65.25, "coolantTemp": 46.0, "throttlePos": 56.25, "startTime": 1589203749.9684837, "steps": 4}, {"speed": 91.75, "rpm": 76.25, "engineLoad": 70.5, "coolantTemp": 71.0, "throttlePos": 63.0, "startTime": 1589203753.9716897, "steps": 4}, {"speed": 56.5, "rpm": 90.25, "engineLoad": 46.25, "coolantTemp": 48.25, "throttlePos": 44.5, "startTime": 1589203757.966568, "steps": 4}, {"speed": 68.5, "rpm": 76.0, "engineLoad": 45.0, "coolantTemp": 72.5, "throttlePos": 56.5, "startTime": 1589203761.9667618, "steps": 4}, {"speed": 99.75, "rpm": 56.5, "engineLoad": 74.25, "coolantTemp": 33.75, "throttlePos": 67.5, "startTime": 1589203765.9709055, "steps": 4}, {"speed": 54.0, "rpm": 31.0, "engineLoad": 73.0, "coolantTemp": 19.75, "throttlePos": 83.5, "startTime": 1589203769.9696867, "steps": 4}, {"speed": 90.5, "rpm": 34.25, "engineLoad": 62.25, "coolantTemp": 67.5, "throttlePos": 54.25, "startTime": 1589203773.9672918, "steps": 4}, {"speed": 56.25, "rpm": 59.75, "engineLoad": 40.25, "coolantTemp": 70.75, "throttlePos": 52.75, "startTime": 1589203777.9676347, "steps": 4}, {"speed": 56.75, "rpm": 78.5, "engineLoad": 32.75, "coolantTemp": 28.5, "throttlePos": 37.75, "startTime": 1589203781.9676347, "steps": 4}, {"speed": 59.0, "rpm": 64.75, "engineLoad": 59.75, "coolantTemp": 52.75, "throttlePos": 56.75, "startTime": 1589203785.9828033, "steps": 4}, {"speed": 63.25, "rpm": 76.5, "engineLoad": 23.0, "coolantTemp": 77.0, "throttlePos": 55.75, "startTime": 1589203789.9665594, "steps": 4}, {"speed": 79.0, "rpm": 73.75, "engineLoad": 40.0, "coolantTemp": 43.75, "throttlePos": 75.75, "startTime": 1589203793.9672332, "steps": 4}, {"speed": 75.75, "rpm": 61.5, "engineLoad": 42.75, "coolantTemp": 56.0, "throttlePos": 74.0, "startTime": 1589203797.9671092, "steps": 4}, {"speed": 79.25, "rpm": 45.75, "engineLoad": 50.25, "coolantTemp": 59.5, "throttlePos": 52.0, "startTime": 1589203801.9733458, "steps": 4}, {"speed": 53.25, "rpm": 49.25, "engineLoad": 64.25, "coolantTemp": 46.0, "throttlePos": 40.5, "startTime": 1589203805.9779372, "steps": 4}, {"speed": 70.25, "rpm": 93.75, "engineLoad": 83.75, "coolantTemp": 60.75, "throttlePos": 19.0, "startTime": 1589203809.977842, "steps": 4}, {"speed": 73.75, "rpm": 51.25, "engineLoad": 45.5, "coolantTemp": 37.25, "throttlePos": 23.25, "startTime": 1589203813.9681573, "steps": 4}, {"speed": 110.25, "rpm": 72.75, "engineLoad": 27.75, "coolantTemp": 27.0, "throttlePos": 45.5, "startTime": 1589203817.9718378, "steps": 4}, {"speed": 29.5, "rpm": 102.5, "engineLoad": 61.25, "coolantTemp": 25.0, "throttlePos": 39.5, "startTime": 1589203821.967507, "steps": 4}, {"speed": 90.75, "rpm": 75.25, "engineLoad": 78.75, "coolantTemp": 39.25, "throttlePos": 49.5, "startTime": 1589203825.9669867, "steps": 4}, {"speed": 82.0, "rpm": 100.0, "engineLoad": 63.75, "coolantTemp": 33.5, "throttlePos": 57.75, "startTime": 1589203829.9669626, "steps": 4}, {"speed": 83.5, "rpm": 94.0, "engineLoad": 42.75, "coolantTemp": 68.5, "throttlePos": 37.5, "startTime": 1589203833.9698083, "steps": 4}, {"speed": 87.75, "rpm": 73.25, "engineLoad": 66.75, "coolantTemp": 75.25, "throttlePos": 70.0, "startTime": 1589203837.9661422, "steps": 4}, {"speed": 59.0, "rpm": 69.0, "engineLoad": 48.0, "coolantTemp": 53.5, "throttlePos": 52.0, "startTime": 1589203841.9686136, "steps": 4}, {"speed": 69.75, "rpm": 79.5, "engineLoad": 57.75, "coolantTemp": 63.75, "throttlePos": 51.25, "startTime": 1589203845.9679148, "steps": 4}, {"speed": 65.0, "rpm": 106.75, "engineLoad": 47.75, "coolantTemp": 22.25, "throttlePos": 76.25, "startTime": 1589203849.9701838, "steps": 4}, {"speed": 100.75, "rpm": 63.0, "engineLoad": 45.25, "coolantTemp": 58.25, "throttlePos": 39.75, "startTime": 1589203853.9676323, "steps": 4}, {"speed": 94.67, "rpm": 61.67, "engineLoad": 60.67, "coolantTemp": 53.0, "throttlePos": 71.0, "startTime": 1589203857.968015, "steps": 3}, {"speed": 86.5, "rpm": 44.0, "engineLoad": 42.25, "coolantTemp": 63.25, "throttlePos": 69.75, "startTime": 1589203861.969076, "steps": 4}, {"speed": 84.0, "rpm": 85.5, "engineLoad": 48.5, "coolantTemp": 47.25, "throttlePos": 53.75, "startTime": 1589203865.9678457, "steps": 4}, {"speed": 67.0, "rpm": 53.5, "engineLoad": 43.25, "coolantTemp": 50.5, "throttlePos": 44.75, "startTime": 1589203869.9673252, "steps": 4}, {"speed": 71.33, "rpm": 92.67, "engineLoad": 57.67, "coolantTemp": 51.33, "throttlePos": 9.67, "startTime": 1589203873.9689178, "steps": 3}, {"speed": 104.0, "rpm": 77.5, "engineLoad": 80.25, "coolantTemp": 65.5, "throttlePos": 47.0, "startTime": 1589203877.9684045, "steps": 4}, {"speed": 62.67, "rpm": 96.67, "engineLoad": 55.67, "coolantTemp": 80.0, "throttlePos": 30.33, "startTime": 1589203881.9675965, "steps": 3}, {"speed": 84.25, "rpm": 80.25, "engineLoad": 43.0, "coolantTemp": 36.5, "throttlePos": 50.5, "startTime": 1589203885.9667194, "steps": 4}, {"speed": 70.0, "rpm": 101.0, "engineLoad": 35.5, "coolantTemp": 74.75, "throttlePos": 26.25, "startTime": 1589203889.9701307, "steps": 4}, {"speed": 82.25, "rpm": 35.75, "engineLoad": 11.5, "coolantTemp": 42.5, "throttlePos": 47.75, "startTime": 1589203893.9691627, "steps": 4}, {"speed": 54.75, "rpm": 76.5, "engineLoad": 28.25, "coolantTemp": 63.25, "throttlePos": 24.5, "startTime": 1589203897.967686, "steps": 4}, {"speed": 112.75, "rpm": 36.0, "engineLoad": 49.0, "coolantTemp": 46.5, "throttlePos": 77.5, "startTime": 1589203901.968101, "steps": 4}, {"speed": 101.75, "rpm": 47.25, "engineLoad": 50.5, "coolantTemp": 44.0, "throttlePos": 41.25, "startTime": 1589203905.9734936, "steps": 4}, {"speed": 91.25, "rpm": 102.5, "engineLoad": 61.75, "coolantTemp": 31.75, "throttlePos": 46.0, "startTime": 1589203909.9679472, "steps": 4}, {"speed": 60.5, "rpm": 85.75, "engineLoad": 50.0, "coolantTemp": 35.25, "throttlePos": 71.25, "startTime": 1589203913.9671314, "steps": 4}, {"speed": 74.0, "rpm": 46.5, "engineLoad": 54.0, "coolantTemp": 69.5, "throttlePos": 59.5, "startTime": 1589203917.9693975, "steps": 4}, {"speed": 50.25, "rpm": 59.25, "engineLoad": 16.25, "coolantTemp": 61.25, "throttlePos": 80.75, "startTime": 1589203921.9691176, "steps": 4}, {"speed": 97.0, "rpm": 106.0, "engineLoad": 47.75, "coolantTemp": 46.0, "throttlePos": 41.0, "startTime": 1589203925.9684768, "steps": 4}, {"speed": 93.75, "rpm": 77.25, "engineLoad": 52.0, "coolantTemp": 51.0, "throttlePos": 72.25, "startTime": 1589203929.9671428, "steps": 4}, {"speed": 58.0, "rpm": 55.5, "engineLoad": 40.5, "coolantTemp": 63.5, "throttlePos": 39.75, "startTime": 1589203933.969759, "steps": 4}, {"speed": 120.25, "rpm": 25.5, "engineLoad": 50.25, "coolantTemp": 47.5, "throttlePos": 52.5, "startTime": 1589203937.966885, "steps": 4}, {"speed": 102.5, "rpm": 98.5, "engineLoad": 34.5, "coolantTemp": 91.25, "throttlePos": 22.75, "startTime": 1589203941.9730597, "steps": 4}, {"speed": 70.0, "rpm": 101.33, "engineLoad": 59.0, "coolantTemp": 46.0, "throttlePos": 41.67, "startTime": 1589203945.968075, "steps": 3}, {"speed": 51.0, "rpm": 80.5, "engineLoad": 51.25, "coolantTemp": 34.75, "throttlePos": 54.25, "startTime": 1589203949.9700034, "steps": 4}, {"speed": 38.5, "rpm": 58.0, "engineLoad": 39.75, "coolantTemp": 47.0, "throttlePos": 53.25, "startTime": 1589203953.9693696, "steps": 4}, {"speed": 68.75, "rpm": 86.75, "engineLoad": 58.0, "coolantTemp": 35.5, "throttlePos": 50.75, "startTime": 1589203957.9713314, "steps": 4}, {"speed": 72.5, "rpm": 64.75, "engineLoad": 46.5, "coolantTemp": 44.0, "throttlePos": 33.0, "startTime": 1589203961.967125, "steps": 4}, {"speed": 109.25, "rpm": 71.0, "engineLoad": 58.5, "coolantTemp": 47.25, "throttlePos": 55.75, "startTime": 1589203965.971432, "steps": 4}, {"speed": 48.25, "rpm": 85.75, "engineLoad": 54.25, "coolantTemp": 38.75, "throttlePos": 31.5, "startTime": 1589203969.966937, "steps": 4}, {"speed": 72.25, "rpm": 57.75, "engineLoad": 46.25, "coolantTemp": 53.5, "throttlePos": 51.75, "startTime": 1589203973.9665663, "steps": 4}, {"speed": 101.5, "rpm": 70.25, "engineLoad": 72.75, "coolantTemp": 46.5, "throttlePos": 39.75, "startTime": 1589203977.9672182, "steps": 4}, {"speed": 51.25, "rpm": 34.0, "engineLoad": 62.75, "coolantTemp": 36.75, "throttlePos": 56.25, "startTime": 1589203981.9679203, "steps": 4}, {"speed": 121.0, "rpm": 64.0, "engineLoad": 32.25, "coolantTemp": 12.75, "throttlePos": 22.75, "startTime": 1589203985.966468, "steps": 4}, {"speed": 78.75, "rpm": 93.75, "engineLoad": 31.25, "coolantTemp": 28.0, "throttlePos": 29.0, "startTime": 1589203989.9691024, "steps": 4}, {"speed": 60.0, "rpm": 53.5, "engineLoad": 55.0, "coolantTemp": 44.75, "throttlePos": 71.0, "startTime": 1589203993.9677575, "steps": 4}, {"speed": 98.75, "rpm": 61.5, "engineLoad": 71.75, "coolantTemp": 77.0, "throttlePos": 59.0, "startTime": 1589203997.9705446, "steps": 4}, {"speed": 83.25, "rpm": 31.0, "engineLoad": 59.25, "coolantTemp": 59.75, "throttlePos": 51.5, "startTime": 1589204001.9687142, "steps": 4}, {"speed": 81.67, "rpm": 51.33, "engineLoad": 23.0, "coolantTemp": 59.0, "throttlePos": 62.33, "startTime": 1589204005.967565, "steps": 3}, {"speed": 67.0, "rpm": 69.5, "engineLoad": 51.25, "coolantTemp": 45.25, "throttlePos": 38.5, "startTime": 1589204009.9685004, "steps": 4}, {"speed": 65.0, "rpm": 119.75, "engineLoad": 63.75, "coolantTemp": 43.0, "throttlePos": 56.75, "startTime": 1589204013.9687824, "steps": 4}, {"speed": 84.0, "rpm": 94.5, "engineLoad": 37.25, "coolantTemp": 65.0, "throttlePos": 32.75, "startTime": 1589204018.2725058, "steps": 4}, {"speed": 84.75, "rpm": 81.75, "engineLoad": 57.75, "coolantTemp": 54.5, "throttlePos": 52.0, "startTime": 1589204021.9660769, "steps": 4}, {"speed": 100.75, "rpm": 79.25, "engineLoad": 65.0, "coolantTemp": 50.25, "throttlePos": 31.75, "startTime": 1589204025.970387, "steps": 4}, {"speed": 45.33, "rpm": 116.33, "engineLoad": 72.67, "coolantTemp": 54.0, "throttlePos": 58.33, "startTime": 1589204029.9679341, "steps": 3}, {"speed": 100.75, "rpm": 85.5, "engineLoad": 84.5, "coolantTemp": 33.25, "throttlePos": 53.0, "startTime": 1589204033.9666634, "steps": 4}, {"speed": 77.75, "rpm": 47.0, "engineLoad": 59.5, "coolantTemp": 37.25, "throttlePos": 44.0, "startTime": 1589204037.9689655, "steps": 4}, {"speed": 89.0, "rpm": 56.0, "engineLoad": 50.5, "coolantTemp": 50.25, "throttlePos": 64.5, "startTime": 1589204041.9691017, "steps": 4}, {"speed": 77.67, "rpm": 39.67, "engineLoad": 43.67, "coolantTemp": 60.33, "throttlePos": 46.33, "startTime": 1589204045.9741259, "steps": 3}, {"speed": 90.5, "rpm": 86.75, "engineLoad": 43.0, "coolantTemp": 48.75, "throttlePos": 65.5, "startTime": 1589204049.9679258, "steps": 4}, {"speed": 80.75, "rpm": 71.25, "engineLoad": 39.75, "coolantTemp": 54.25, "throttlePos": 41.5, "startTime": 1589204053.967943, "steps": 4}, {"speed": 76.25, "rpm": 71.5, "engineLoad": 59.75, "coolantTemp": 62.25, "throttlePos": 17.75, "startTime": 1589204057.9692197, "steps": 4}, {"speed": 56.25, "rpm": 79.75, "engineLoad": 65.75, "coolantTemp": 39.25, "throttlePos": 51.0, "startTime": 1589204061.973252, "steps": 4}, {"speed": 60.67, "rpm": 108.33, "engineLoad": 76.67, "coolantTemp": 35.67, "throttlePos": 36.0, "startTime": 1589204065.9691887, "steps": 3}, {"speed": 76.25, "rpm": 52.25, "engineLoad": 81.5, "coolantTemp": 58.25, "throttlePos": 44.75, "startTime": 1589204069.9678807, "steps": 4}, {"speed": 121.0, "rpm": 76.25, "engineLoad": 56.0, "coolantTemp": 50.5, "throttlePos": 68.5, "startTime": 1589204073.96946, "steps": 4}, {"speed": 75.5, "rpm": 104.5, "engineLoad": 39.0, "coolantTemp": 56.5, "throttlePos": 26.0, "startTime": 1589204077.9682891, "steps": 4}, {"speed": 97.0, "rpm": 78.5, "engineLoad": 45.75, "coolantTemp": 54.25, "throttlePos": 48.0, "startTime": 1589204081.9680755, "steps": 4}, {"speed": 61.33, "rpm": 27.33, "engineLoad": 75.67, "coolantTemp": 29.67, "throttlePos": 47.0, "startTime": 1589204085.9678104, "steps": 3}, {"speed": 35.5, "rpm": 93.0, "engineLoad": 36.5, "coolantTemp": 61.75, "throttlePos": 48.0, "startTime": 1589204089.9695587, "steps": 4}, {"speed": 96.0, "rpm": 57.75, "engineLoad": 34.75, "coolantTemp": 43.5, "throttlePos": 73.25, "startTime": 1589204093.9685657, "steps": 4}, {"speed": 58.67, "rpm": 68.33, "engineLoad": 49.0, "coolantTemp": 80.67, "throttlePos": 79.0, "startTime": 1589204097.9687355, "steps": 3}, {"speed": 84.75, "rpm": 83.5, "engineLoad": 20.75, "coolantTemp": 47.5, "throttlePos": 41.5, "startTime": 1589204101.9682188, "steps": 4}, {"speed": 83.75, "rpm": 70.25, "engineLoad": 40.5, "coolantTemp": 60.0, "throttlePos": 50.5, "startTime": 1589204105.9714315, "steps": 4}, {"speed": 46.0, "rpm": 106.0, "engineLoad": 31.33, "coolantTemp": 44.33, "throttlePos": 61.67, "startTime": 1589204109.971072, "steps": 3}, {"speed": 114.0, "rpm": 95.75, "engineLoad": 45.0, "coolantTemp": 53.0, "throttlePos": 51.5, "startTime": 1589204113.9675567, "steps": 4}, {"speed": 55.0, "rpm": 36.75, "engineLoad": 28.25, "coolantTemp": 43.5, "throttlePos": 35.75, "startTime": 1589204117.9685817, "steps": 4}, {"speed": 83.25, "rpm": 79.25, "engineLoad": 58.5, "coolantTemp": 44.5, "throttlePos": 60.25, "startTime": 1589204121.9691758, "steps": 4}, {"speed": 90.75, "rpm": 112.25, "engineLoad": 49.5, "coolantTemp": 17.25, "throttlePos": 74.0, "startTime": 1589204125.9681468, "steps": 4}, {"speed": 54.25, "rpm": 92.5, "engineLoad": 47.5, "coolantTemp": 37.25, "throttlePos": 50.5, "startTime": 1589204129.9763324, "steps": 4}, {"speed": 61.0, "rpm": 51.75, "engineLoad": 19.75, "coolantTemp": 8.75, "throttlePos": 37.5, "startTime": 1589204133.9710667, "steps": 4}, {"speed": 66.5, "rpm": 78.75, "engineLoad": 33.5, "coolantTemp": 32.0, "throttlePos": 45.0, "startTime": 1589204137.9694002, "steps": 4}, {"speed": 94.0, "rpm": 73.0, "engineLoad": 48.75, "coolantTemp": 65.25, "throttlePos": 39.0, "startTime": 1589204141.9773343, "steps": 4}, {"speed": 72.5, "rpm": 67.0, "engineLoad": 36.5, "coolantTemp": 36.0, "throttlePos": 56.75, "startTime": 1589204145.9685004, "steps": 4}, {"speed": 62.67, "rpm": 73.67, "engineLoad": 38.0, "coolantTemp": 72.0, "throttlePos": 37.67, "startTime": 1589204149.9703178, "steps": 3}, {"speed": 86.0, "rpm": 83.25, "engineLoad": 67.5, "coolantTemp": 60.75, "throttlePos": 55.0, "startTime": 1589204153.969093, "steps": 4}, {"speed": 54.25, "rpm": 77.25, "engineLoad": 49.5, "coolantTemp": 62.25, "throttlePos": 55.5, "startTime": 1589204157.975536, "steps": 4}, {"speed": 113.0, "rpm": 98.5, "engineLoad": 49.0, "coolantTemp": 43.25, "throttlePos": 55.75, "startTime": 1589204161.969159, "steps": 4}, {"speed": 78.25, "rpm": 80.0, "engineLoad": 64.25, "coolantTemp": 54.25, "throttlePos": 57.75, "startTime": 1589204165.9711628, "steps": 4}, {"speed": 103.5, "rpm": 52.0, "engineLoad": 40.0, "coolantTemp": 53.0, "throttlePos": 24.0, "startTime": 1589204169.9686868, "steps": 4}, {"speed": 51.75, "rpm": 85.75, "engineLoad": 48.0, "coolantTemp": 24.75, "throttlePos": 85.0, "startTime": 1589204173.9733844, "steps": 4}, {"speed": 56.5, "rpm": 123.75, "engineLoad": 16.0, "coolantTemp": 43.5, "throttlePos": 36.25, "startTime": 1589204177.9676852, "steps": 4}, {"speed": 92.25, "rpm": 101.25, "engineLoad": 68.5, "coolantTemp": 61.5, "throttlePos": 64.5, "startTime": 1589204181.9709399, "steps": 4}, {"speed": 79.25, "rpm": 77.25, "engineLoad": 46.0, "coolantTemp": 56.0, "throttlePos": 47.0, "startTime": 1589204185.971652, "steps": 4}, {"speed": 55.25, "rpm": 69.75, "engineLoad": 28.0, "coolantTemp": 93.25, "throttlePos": 61.75, "startTime": 1589204189.96836, "steps": 4}, {"speed": 110.0, "rpm": 41.25, "engineLoad": 31.75, "coolantTemp": 54.75, "throttlePos": 73.75, "startTime": 1589204193.968787, "steps": 4}, {"speed": 65.25, "rpm": 24.25, "engineLoad": 34.0, "coolantTemp": 51.5, "throttlePos": 46.25, "startTime": 1589204197.9693978, "steps": 4}, {"speed": 76.5, "rpm": 74.0, "engineLoad": 63.5, "coolantTemp": 31.75, "throttlePos": 67.75, "startTime": 1589204201.9689298, "steps": 4}, {"speed": 37.5, "rpm": 73.75, "engineLoad": 34.75, "coolantTemp": 32.75, "throttlePos": 27.75, "startTime": 1589204205.9693267, "steps": 4}, {"speed": 111.5, "rpm": 74.75, "engineLoad": 70.25, "coolantTemp": 24.0, "throttlePos": 58.0, "startTime": 1589204209.9681165, "steps": 4}, {"speed": 80.33, "rpm": 72.0, "engineLoad": 24.33, "coolantTemp": 51.33, "throttlePos": 35.67, "startTime": 1589204213.9705229, "steps": 3}, {"speed": 61.0, "rpm": 80.25, "engineLoad": 45.0, "coolantTemp": 67.75, "throttlePos": 48.75, "startTime": 1589204217.9706023, "steps": 4}, {"speed": 90.75, "rpm": 91.25, "engineLoad": 45.0, "coolantTemp": 38.25, "throttlePos": 40.5, "startTime": 1589204221.9681976, "steps": 4}, {"speed": 79.0, "rpm": 51.25, "engineLoad": 50.5, "coolantTemp": 45.0, "throttlePos": 62.5, "startTime": 1589204225.9675224, "steps": 4}, {"speed": 57.75, "rpm": 109.5, "engineLoad": 72.25, "coolantTemp": 55.25, "throttlePos": 18.0, "startTime": 1589204229.9679132, "steps": 4}, {"speed": 28.67, "rpm": 87.67, "engineLoad": 66.0, "coolantTemp": 43.0, "throttlePos": 41.67, "startTime": 1589204233.9698799, "steps": 3}, {"speed": 53.5, "rpm": 81.5, "engineLoad": 40.0, "coolantTemp": 49.0, "throttlePos": 60.75, "startTime": 1589204237.9669452, "steps": 4}, {"speed": 93.25, "rpm": 97.0, "engineLoad": 40.25, "coolantTemp": 38.75, "throttlePos": 52.0, "startTime": 1589204241.9686909, "steps": 4}, {"speed": 59.75, "rpm": 20.75, "engineLoad": 25.5, "coolantTemp": 62.0, "throttlePos": 58.75, "startTime": 1589204245.9687076, "steps": 4}, {"speed": 94.25, "rpm": 66.5, "engineLoad": 47.5, "coolantTemp": 27.0, "throttlePos": 31.5, "startTime": 1589204249.9787445, "steps": 4}, {"speed": 110.67, "rpm": 40.33, "engineLoad": 26.67, "coolantTemp": 25.33, "throttlePos": 67.0, "startTime": 1589204253.9681933, "steps": 3}]}, "12": {"startTime": "Tuesday May, 12 2020 05:27:19", "duration": 35.5, "avSpeed": 80.59, "avRPM": 81.0, "avEngineLoad": 47.36, "avCoolantTemp": 50.48, "avThrottlePos": 52.7, "nSnaps": 10, "snaps": [{"speed": 94.4, "rpm": 106.6, "engineLoad": 46.8, "coolantTemp": 51.0, "throttlePos": 44.0, "startTime": 1589250439.0922947, "steps": 5}, {"speed": 76.08, "rpm": 84.41, "engineLoad": 54.84, "coolantTemp": 58.42, "throttlePos": 39.67, "startTime": 1589250439.376626, "steps": 12}, {"speed": 91.62, "rpm": 68.12, "engineLoad": 39.68, "coolantTemp": 46.69, "throttlePos": 53.51, "startTime": 1589250442.5735044, "steps": 16}, {"speed": 82.74, "rpm": 77.12, "engineLoad": 53.12, "coolantTemp": 46.19, "throttlePos": 64.37, "startTime": 1589250446.5703783, "steps": 16}, {"speed": 86.41, "rpm": 66.27, "engineLoad": 51.01, "coolantTemp": 65.13, "throttlePos": 56.93, "startTime": 1589250450.5701602, "steps": 15}, {"speed": 74.48, "rpm": 86.25, "engineLoad": 49.81, "coolantTemp": 49.13, "throttlePos": 59.19, "startTime": 1589250454.5716493, "steps": 15}, {"speed": 70.33, "rpm": 83.14, "engineLoad": 39.73, "coolantTemp": 51.14, "throttlePos": 49.21, "startTime": 1589250458.5721955, "steps": 15}, {"speed": 85.32, "rpm": 85.69, "engineLoad": 48.32, "coolantTemp": 41.75, "throttlePos": 52.12, "startTime": 1589250462.5713205, "steps": 16}, {"speed": 92.93, "rpm": 62.68, "engineLoad": 49.94, "coolantTemp": 54.44, "throttlePos": 55.13, "startTime": 1589250466.5716507, "steps": 16}, {"speed": 51.56, "rpm": 87.94, "engineLoad": 40.31, "coolantTemp": 40.94, "throttlePos": 52.75, "startTime": 1589250470.5730016, "steps": 16}]}, "13": {"startTime": "Tuesday May, 12 2020 05:28:17", "duration": 13.4, "avSpeed": 73.67, "avRPM": 76.0, "avEngineLoad": 49.91, "avCoolantTemp": 52.27, "avThrottlePos": 51.02, "nSnaps": 4, "snaps": [{"speed": 79.97, "rpm": 73.47, "engineLoad": 48.79, "coolantTemp": 50.96, "throttlePos": 48.02, "startTime": 1589250497.176731, "steps": 45}, {"speed": 65.31, "rpm": 83.88, "engineLoad": 44.26, "coolantTemp": 55.51, "throttlePos": 48.38, "startTime": 1589250498.573918, "steps": 16}, {"speed": 64.76, "rpm": 72.75, "engineLoad": 49.62, "coolantTemp": 51.5, "throttlePos": 51.68, "startTime": 1589250502.5717778, "steps": 16}, {"speed": 84.63, "rpm": 75.62, "engineLoad": 57.0, "coolantTemp": 51.12, "throttlePos": 56.0, "startTime": 1589250506.5699909, "steps": 16}]}, "14": {"startTime": "Tuesday May, 12 2020 05:46:07", "duration": 92.0, "avSpeed": 75.69, "avRPM": 73.0, "avEngineLoad": 47.85, "avCoolantTemp": 51.27, "avThrottlePos": 50.18, "nSnaps": 23, "snaps": [{"speed": 56.87, "rpm": 66.13, "engineLoad": 43.44, "coolantTemp": 45.63, "throttlePos": 57.5, "startTime": 1589251567.0021074, "steps": 16}, {"speed": 74.37, "rpm": 75.68, "engineLoad": 36.25, "coolantTemp": 57.0, "throttlePos": 54.23, "startTime": 1589251571.011299, "steps": 16}, {"speed": 75.57, "rpm": 72.3, "engineLoad": 50.82, "coolantTemp": 57.06, "throttlePos": 37.38, "startTime": 1589251575.0008402, "steps": 16}, {"speed": 64.39, "rpm": 74.41, "engineLoad": 57.47, "coolantTemp": 50.01, "throttlePos": 39.06, "startTime": 1589251579.0030766, "steps": 15}, {"speed": 66.49, "rpm": 55.18, "engineLoad": 54.74, "coolantTemp": 59.51, "throttlePos": 51.56, "startTime": 1589251583.002707, "steps": 16}, {"speed": 72.5, "rpm": 87.44, "engineLoad": 50.12, "coolantTemp": 47.0, "throttlePos": 59.05, "startTime": 1589251587.001308, "steps": 16}, {"speed": 68.0, "rpm": 69.62, "engineLoad": 46.57, "coolantTemp": 48.44, "throttlePos": 45.93, "startTime": 1589251591.003384, "steps": 16}, {"speed": 97.13, "rpm": 80.62, "engineLoad": 41.38, "coolantTemp": 45.5, "throttlePos": 45.63, "startTime": 1589251595.0031486, "steps": 16}, {"speed": 80.32, "rpm": 61.67, "engineLoad": 51.69, "coolantTemp": 59.56, "throttlePos": 62.57, "startTime": 1589251599.0011742, "steps": 16}, {"speed": 84.88, "rpm": 88.18, "engineLoad": 58.44, "coolantTemp": 60.5, "throttlePos": 45.56, "startTime": 1589251603.0007896, "steps": 16}, {"speed": 78.37, "rpm": 66.93, "engineLoad": 41.94, "coolantTemp": 54.94, "throttlePos": 53.68, "startTime": 1589251607.0237768, "steps": 16}, {"speed": 73.07, "rpm": 78.12, "engineLoad": 48.18, "coolantTemp": 47.68, "throttlePos": 45.76, "startTime": 1589251611.0033576, "steps": 16}, {"speed": 88.31, "rpm": 75.88, "engineLoad": 59.87, "coolantTemp": 62.38, "throttlePos": 54.81, "startTime": 1589251615.003612, "steps": 16}, {"speed": 52.81, "rpm": 63.69, "engineLoad": 50.44, "coolantTemp": 44.76, "throttlePos": 41.24, "startTime": 1589251619.0018811, "steps": 16}, {"speed": 69.81, "rpm": 69.12, "engineLoad": 59.81, "coolantTemp": 46.44, "throttlePos": 51.26, "startTime": 1589251623.0026457, "steps": 16}, {"speed": 73.37, "rpm": 85.43, "engineLoad": 37.81, "coolantTemp": 48.69, "throttlePos": 58.12, "startTime": 1589251627.0012562, "steps": 16}, {"speed": 96.38, "rpm": 81.5, "engineLoad": 49.38, "coolantTemp": 51.87, "throttlePos": 51.26, "startTime": 1589251631.001183, "steps": 16}, {"speed": 71.69, "rpm": 77.49, "engineLoad": 44.12, "coolantTemp": 61.86, "throttlePos": 53.25, "startTime": 1589251635.0045028, "steps": 16}, {"speed": 79.59, "rpm": 75.21, "engineLoad": 43.66, "coolantTemp": 43.27, "throttlePos": 45.01, "startTime": 1589251639.003146, "steps": 15}, {"speed": 74.93, "rpm": 83.06, "engineLoad": 42.24, "coolantTemp": 54.07, "throttlePos": 63.32, "startTime": 1589251643.0001395, "steps": 16}, {"speed": 72.38, "rpm": 75.19, "engineLoad": 50.38, "coolantTemp": 43.32, "throttlePos": 46.99, "startTime": 1589251647.0045698, "steps": 16}, {"speed": 89.5, "rpm": 70.57, "engineLoad": 48.37, "coolantTemp": 41.75, "throttlePos": 47.87, "startTime": 1589251651.0045662, "steps": 16}, {"speed": 80.0, "rpm": 61.01, "engineLoad": 33.63, "coolantTemp": 48.19, "throttlePos": 43.25, "startTime": 1589251655.003023, "steps": 16}]}, "15": {"startTime": "Tuesday May, 12 2020 05:49:23", "duration": 7.8, "avSpeed": 35.53, "avRPM": 59.0, "avEngineLoad": 32.15, "avCoolantTemp": 31.65, "avThrottlePos": 34.61, "nSnaps": 3, "snaps": [{"speed": 0, "rpm": 0, "engineLoad": 0, "coolantTemp": 0, "throttlePos": 0, "startTime": 1589251763.24808, "steps": 0}, {"speed": 59.77, "rpm": 101.64, "engineLoad": 54.46, "coolantTemp": 48.76, "throttlePos": 54.71, "startTime": 1589251763.5063899, "steps": 17}, {"speed": 46.81, "rpm": 76.38, "engineLoad": 42.0, "coolantTemp": 46.2, "throttlePos": 49.12, "startTime": 1589251767.002185, "steps": 16}]}, "16": {"startTime": "Tuesday May, 12 2020 05:49:45", "duration": 1.2, "avSpeed": 81.97, "avRPM": 82.0, "avEngineLoad": 51.56, "avCoolantTemp": 54.12, "avThrottlePos": 47.39, "nSnaps": 1, "snaps": [{"speed": 81.97, "rpm": 82.5, "engineLoad": 51.56, "coolantTemp": 54.12, "throttlePos": 47.39, "startTime": 1589251785.8297555, "steps": 45}]}, "17": {"startTime": "Tuesday May, 12 2020 05:50:49", "duration": 13.2, "avSpeed": 82.05, "avRPM": 79.0, "avEngineLoad": 47.24, "avCoolantTemp": 49.62, "avThrottlePos": 51.9, "nSnaps": 4, "snaps": [{"speed": 83.78, "rpm": 75.39, "engineLoad": 47.36, "coolantTemp": 49.07, "throttlePos": 43.55, "startTime": 1589251849.7647316, "steps": 90}, {"speed": 89.27, "rpm": 90.35, "engineLoad": 43.93, "coolantTemp": 39.85, "throttlePos": 57.74, "startTime": 1589251851.0045722, "steps": 15}, {"speed": 78.94, "rpm": 87.06, "engineLoad": 54.49, "coolantTemp": 56.38, "throttlePos": 49.44, "startTime": 1589251855.0020525, "steps": 16}, {"speed": 76.19, "rpm": 63.75, "engineLoad": 43.19, "coolantTemp": 53.19, "throttlePos": 56.87, "startTime": 1589251859.0015612, "steps": 16}]}, "18": {"startTime": "Tuesday May, 12 2020 05:51:13", "duration": 33.3, "avSpeed": 73.91, "avRPM": 74.0, "avEngineLoad": 50.53, "avCoolantTemp": 49.96, "avThrottlePos": 48.85, "nSnaps": 9, "snaps": [{"speed": 84.45, "rpm": 66.2, "engineLoad": 56.17, "coolantTemp": 50.03, "throttlePos": 51.71, "startTime": 1589251873.6735542, "steps": 31}, {"speed": 48.68, "rpm": 80.5, "engineLoad": 50.08, "coolantTemp": 49.56, "throttlePos": 52.06, "startTime": 1589251875.0090377, "steps": 16}, {"speed": 75.76, "rpm": 91.87, "engineLoad": 54.37, "coolantTemp": 54.62, "throttlePos": 40.19, "startTime": 1589251879.0010886, "steps": 16}, {"speed": 72.31, "rpm": 93.44, "engineLoad": 52.87, "coolantTemp": 52.99, "throttlePos": 53.43, "startTime": 1589251883.0007207, "steps": 16}, {"speed": 82.38, "rpm": 66.56, "engineLoad": 50.19, "coolantTemp": 56.43, "throttlePos": 47.62, "startTime": 1589251887.001023, "steps": 16}, {"speed": 68.51, "rpm": 52.25, "engineLoad": 52.99, "coolantTemp": 37.5, "throttlePos": 49.31, "startTime": 1589251891.003148, "steps": 16}, {"speed": 90.18, "rpm": 76.88, "engineLoad": 38.06, "coolantTemp": 56.63, "throttlePos": 57.68, "startTime": 1589251895.0037196, "steps": 16}, {"speed": 79.06, "rpm": 71.93, "engineLoad": 55.68, "coolantTemp": 49.75, "throttlePos": 35.25, "startTime": 1589251899.0036256, "steps": 16}, {"speed": 63.81, "rpm": 65.37, "engineLoad": 44.38, "coolantTemp": 42.13, "throttlePos": 52.44, "startTime": 1589251903.0051155, "steps": 16}]}, "19": {"startTime": "Tuesday May, 12 2020 05:51:48", "duration": 2.1, "avSpeed": 56.84, "avRPM": 87.0, "avEngineLoad": 44.08, "avCoolantTemp": 61.84, "avThrottlePos": 35.0, "nSnaps": 1, "snaps": [{"speed": 56.84, "rpm": 87.42, "engineLoad": 44.08, "coolantTemp": 61.84, "throttlePos": 35.0, "startTime": 1589251908.8550541, "steps": 12}]}, "20": {"startTime": "Tuesday May, 12 2020 05:51:53", "duration": 29.5, "avSpeed": 67.78, "avRPM": 83.0, "avEngineLoad": 47.52, "avCoolantTemp": 48.55, "avThrottlePos": 48.91, "nSnaps": 8, "snaps": [{"speed": 64.63, "rpm": 83.86, "engineLoad": 44.86, "coolantTemp": 54.87, "throttlePos": 38.35, "startTime": 1589251913.4682703, "steps": 14}, {"speed": 64.19, "rpm": 84.45, "engineLoad": 50.55, "coolantTemp": 48.38, "throttlePos": 57.76, "startTime": 1589251915.0077286, "steps": 16}, {"speed": 87.88, "rpm": 80.68, "engineLoad": 39.14, "coolantTemp": 56.69, "throttlePos": 42.68, "startTime": 1589251919.0101156, "steps": 16}, {"speed": 70.07, "rpm": 80.0, "engineLoad": 59.7, "coolantTemp": 45.06, "throttlePos": 52.0, "startTime": 1589251923.0019798, "steps": 16}, {"speed": 74.07, "rpm": 76.75, "engineLoad": 51.06, "coolantTemp": 52.37, "throttlePos": 46.19, "startTime": 1589251927.002712, "steps": 16}, {"speed": 54.46, "rpm": 83.13, "engineLoad": 40.14, "coolantTemp": 45.66, "throttlePos": 41.2, "startTime": 1589251931.0038788, "steps": 15}, {"speed": 58.18, "rpm": 98.94, "engineLoad": 48.94, "coolantTemp": 46.74, "throttlePos": 59.62, "startTime": 1589251935.0008326, "steps": 16}, {"speed": 68.76, "rpm": 76.0, "engineLoad": 45.76, "coolantTemp": 38.69, "throttlePos": 53.44, "startTime": 1589251939.0056834, "steps": 16}]}, "21": {"startTime": "Tuesday May, 12 2020 05:52:25", "duration": 1.6, "avSpeed": 62.1, "avRPM": 79.0, "avEngineLoad": 76.69, "avCoolantTemp": 42.5, "avThrottlePos": 32.1, "nSnaps": 1, "snaps": [{"speed": 62.1, "rpm": 79.1, "engineLoad": 76.69, "coolantTemp": 42.5, "throttlePos": 32.1, "startTime": 1589251945.4410398, "steps": 10}]}, "22": {"startTime": "Tuesday May, 12 2020 05:52:38", "duration": 100.7, "avSpeed": 78.92, "avRPM": 68.0, "avEngineLoad": 48.91, "avCoolantTemp": 48.71, "avThrottlePos": 48.02, "nSnaps": 26, "snaps": [{"speed": 73.25, "rpm": 73.58, "engineLoad": 49.39, "coolantTemp": 48.37, "throttlePos": 58.28, "startTime": 1589251958.3342848, "steps": 28}, {"speed": 73.07, "rpm": 67.95, "engineLoad": 47.51, "coolantTemp": 33.44, "throttlePos": 55.12, "startTime": 1589251959.0057025, "steps": 16}, {"speed": 72.06, "rpm": 83.75, "engineLoad": 51.75, "coolantTemp": 44.19, "throttlePos": 46.75, "startTime": 1589251963.0016623, "steps": 16}, {"speed": 100.13, "rpm": 63.88, "engineLoad": 43.32, "coolantTemp": 36.25, "throttlePos": 43.38, "startTime": 1589251967.003104, "steps": 16}, {"speed": 67.57, "rpm": 82.69, "engineLoad": 65.12, "coolantTemp": 57.87, "throttlePos": 40.88, "startTime": 1589251971.0062556, "steps": 16}, {"speed": 81.12, "rpm": 42.38, "engineLoad": 41.69, "coolantTemp": 59.94, "throttlePos": 49.0, "startTime": 1589251975.0025182, "steps": 16}, {"speed": 82.69, "rpm": 71.82, "engineLoad": 53.32, "coolantTemp": 34.26, "throttlePos": 45.68, "startTime": 1589251979.003473, "steps": 16}, {"speed": 75.17, "rpm": 62.25, "engineLoad": 55.7, "coolantTemp": 52.95, "throttlePos": 40.44, "startTime": 1589251983.0047011, "steps": 16}, {"speed": 63.54, "rpm": 63.06, "engineLoad": 40.13, "coolantTemp": 50.93, "throttlePos": 49.8, "startTime": 1589251987.0038602, "steps": 15}, {"speed": 89.2, "rpm": 68.92, "engineLoad": 52.07, "coolantTemp": 54.6, "throttlePos": 54.33, "startTime": 1589251991.0022001, "steps": 15}, {"speed": 82.38, "rpm": 74.63, "engineLoad": 38.32, "coolantTemp": 45.67, "throttlePos": 49.82, "startTime": 1589251995.0028265, "steps": 16}, {"speed": 107.62, "rpm": 62.75, "engineLoad": 38.81, "coolantTemp": 53.37, "throttlePos": 41.56, "startTime": 1589251999.0047395, "steps": 16}, {"speed": 92.56, "rpm": 74.24, "engineLoad": 52.87, "coolantTemp": 43.69, "throttlePos": 58.88, "startTime": 1589252003.0036287, "steps": 16}, {"speed": 90.67, "rpm": 52.26, "engineLoad": 35.6, "coolantTemp": 46.99, "throttlePos": 70.01, "startTime": 1589252007.002847, "steps": 15}, {"speed": 82.68, "rpm": 82.06, "engineLoad": 42.75, "coolantTemp": 56.32, "throttlePos": 42.88, "startTime": 1589252011.0032778, "steps": 16}, {"speed": 82.01, "rpm": 74.12, "engineLoad": 53.88, "coolantTemp": 53.38, "throttlePos": 40.64, "startTime": 1589252015.0039577, "steps": 16}, {"speed": 80.69, "rpm": 68.57, "engineLoad": 46.74, "coolantTemp": 57.62, "throttlePos": 44.17, "startTime": 1589252019.0038455, "steps": 16}, {"speed": 76.5, "rpm": 64.06, "engineLoad": 55.31, "coolantTemp": 41.57, "throttlePos": 38.81, "startTime": 1589252023.0053468, "steps": 16}, {"speed": 67.56, "rpm": 68.07, "engineLoad": 52.63, "coolantTemp": 50.01, "throttlePos": 43.13, "startTime": 1589252027.0038297, "steps": 16}, {"speed": 72.0, "rpm": 52.63, "engineLoad": 54.62, "coolantTemp": 46.25, "throttlePos": 47.87, "startTime": 1589252031.003412, "steps": 16}, {"speed": 84.33, "rpm": 63.06, "engineLoad": 49.87, "coolantTemp": 58.0, "throttlePos": 51.12, "startTime": 1589252035.0032077, "steps": 16}, {"speed": 76.13, "rpm": 69.38, "engineLoad": 47.26, "coolantTemp": 49.88, "throttlePos": 48.06, "startTime": 1589252039.0039754, "steps": 16}, {"speed": 86.58, "rpm": 63.75, "engineLoad": 42.19, "coolantTemp": 52.45, "throttlePos": 50.31, "startTime": 1589252043.0031953, "steps": 16}, {"speed": 58.34, "rpm": 63.2, "engineLoad": 50.27, "coolantTemp": 46.33, "throttlePos": 42.06, "startTime": 1589252047.0032897, "steps": 15}, {"speed": 61.55, "rpm": 89.5, "engineLoad": 47.63, "coolantTemp": 47.39, "throttlePos": 37.01, "startTime": 1589252051.0016074, "steps": 16}, {"speed": 72.18, "rpm": 76.37, "engineLoad": 62.62, "coolantTemp": 44.74, "throttlePos": 58.5, "startTime": 1589252055.0025558, "steps": 16}]}, "23": {"startTime": "Tuesday May, 12 2020 05:54:57", "duration": 5.7, "avSpeed": 80.96, "avRPM": 75.0, "avEngineLoad": 43.64, "avCoolantTemp": 43.05, "avThrottlePos": 51.31, "nSnaps": 2, "snaps": [{"speed": 96.11, "rpm": 82.4, "engineLoad": 42.8, "coolantTemp": 40.4, "throttlePos": 58.0, "startTime": 1589252097.3183825, "steps": 10}, {"speed": 65.81, "rpm": 68.01, "engineLoad": 44.49, "coolantTemp": 45.69, "throttlePos": 44.62, "startTime": 1589252099.0074487, "steps": 16}]}, "24": {"startTime": "Tuesday May, 12 2020 05:55:12", "duration": 38.2, "avSpeed": 74.21, "avRPM": 72.0, "avEngineLoad": 49.11, "avCoolantTemp": 49.99, "avThrottlePos": 48.03, "nSnaps": 10, "snaps": [{"speed": 77.51, "rpm": 77.8, "engineLoad": 50.06, "coolantTemp": 42.76, "throttlePos": 48.72, "startTime": 1589252112.8295758, "steps": 29}, {"speed": 65.57, "rpm": 74.01, "engineLoad": 40.43, "coolantTemp": 54.93, "throttlePos": 45.38, "startTime": 1589252115.0088189, "steps": 16}, {"speed": 67.93, "rpm": 68.26, "engineLoad": 37.88, "coolantTemp": 53.88, "throttlePos": 47.38, "startTime": 1589252119.0055435, "steps": 16}, {"speed": 88.98, "rpm": 83.26, "engineLoad": 53.99, "coolantTemp": 58.51, "throttlePos": 61.99, "startTime": 1589252123.004751, "steps": 16}, {"speed": 68.49, "rpm": 73.49, "engineLoad": 56.25, "coolantTemp": 45.38, "throttlePos": 43.45, "startTime": 1589252127.0027404, "steps": 16}, {"speed": 87.75, "rpm": 78.94, "engineLoad": 49.69, "coolantTemp": 54.26, "throttlePos": 39.0, "startTime": 1589252131.0034893, "steps": 16}, {"speed": 77.76, "rpm": 72.43, "engineLoad": 62.62, "coolantTemp": 47.2, "throttlePos": 50.18, "startTime": 1589252135.0041716, "steps": 16}, {"speed": 69.57, "rpm": 65.68, "engineLoad": 50.26, "coolantTemp": 51.94, "throttlePos": 46.56, "startTime": 1589252139.002971, "steps": 16}, {"speed": 50.19, "rpm": 62.73, "engineLoad": 50.67, "coolantTemp": 40.47, "throttlePos": 49.59, "startTime": 1589252143.1992831, "steps": 15}, {"speed": 88.31, "rpm": 59.93, "engineLoad": 39.24, "coolantTemp": 50.49, "throttlePos": 48.02, "startTime": 1589252147.0030115, "steps": 16}]}, "25": {"startTime": "Tuesday May, 12 2020 05:55:55", "duration": 11.5, "avSpeed": 49.5, "avRPM": 52.0, "avEngineLoad": 36.52, "avCoolantTemp": 31.35, "avThrottlePos": 33.45, "nSnaps": 4, "snaps": [{"speed": 0, "rpm": 0, "engineLoad": 0, "coolantTemp": 0, "throttlePos": 0, "startTime": 1589252155.4918659, "steps": 0}, {"speed": 81.11, "rpm": 60.77, "engineLoad": 49.51, "coolantTemp": 31.95, "throttlePos": 48.17, "startTime": 1589252155.5357475, "steps": 18}, {"speed": 52.57, "rpm": 71.69, "engineLoad": 48.56, "coolantTemp": 42.19, "throttlePos": 44.25, "startTime": 1589252159.003923, "steps": 16}, {"speed": 64.32, "rpm": 74.18, "engineLoad": 48.0, "coolantTemp": 51.26, "throttlePos": 41.37, "startTime": 1589252163.0040176, "steps": 16}]}, "26": {"startTime": "Tuesday May, 12 2020 05:56:10", "duration": 0.8, "avSpeed": 95.17, "avRPM": 79.0, "avEngineLoad": 50.83, "avCoolantTemp": 55.33, "avThrottlePos": 51.83, "nSnaps": 1, "snaps": [{"speed": 95.17, "rpm": 78.67, "engineLoad": 50.83, "coolantTemp": 55.33, "throttlePos": 51.83, "startTime": 1589252170.2461526, "steps": 6}]}, "27": {"startTime": "Tuesday May, 12 2020 05:56:14", "duration": 0.7, "avSpeed": 77.81, "avRPM": 91.0, "avEngineLoad": 54.09, "avCoolantTemp": 42.91, "avThrottlePos": 53.0, "nSnaps": 1, "snaps": [{"speed": 77.81, "rpm": 90.64, "engineLoad": 54.09, "coolantTemp": 42.91, "throttlePos": 53.0, "startTime": 1589252174.3193002, "steps": 11}]}, "28": {"startTime": "Tuesday May, 12 2020 05:56:52", "duration": 2.5, "avSpeed": 0.0, "avRPM": 0.0, "avEngineLoad": 0.0, "avCoolantTemp": 0.0, "avThrottlePos": 0.0, "nSnaps": 1, "snaps": [{"speed": 0, "rpm": 0, "engineLoad": 0, "coolantTemp": 0, "throttlePos": 0, "startTime": 1589252212.7301602, "steps": 0}]}, "29": {"startTime": "Tuesday May, 12 2020 05:56:57", "duration": 64.0, "avSpeed": 108.72, "avRPM": 6169.0, "avEngineLoad": 0.0, "avCoolantTemp": 7.75, "avThrottlePos": 33.53, "nSnaps": 16, "snaps": [{"speed": 0.0, "rpm": 0.0, "engineLoad": 0.0, "coolantTemp": 0.0, "throttlePos": 0.0, "startTime": 1589252217.8267448, "steps": 9}, {"speed": 0.0, "rpm": 0.0, "engineLoad": 0.0, "coolantTemp": 0.0, "throttlePos": 0.0, "startTime": 1589252221.8365123, "steps": 16}, {"speed": 0.0, "rpm": 3513.84, "engineLoad": 0.0, "coolantTemp": 0.0, "throttlePos": 0.0, "startTime": 1589252225.82973, "steps": 16}, {"speed": 0.0, "rpm": 7953.87, "engineLoad": 0.0, "coolantTemp": 0.0, "throttlePos": 0.0, "startTime": 1589252229.831834, "steps": 16}, {"speed": 0.0, "rpm": 4311.5, "engineLoad": 0.0, "coolantTemp": 14.12, "throttlePos": 44.71, "startTime": 1589252233.8305516, "steps": 16}, {"speed": 113.82, "rpm": 4311.5, "engineLoad": 0.0, "coolantTemp": -32.0, "throttlePos": 44.71, "startTime": 1589252237.8299997, "steps": 16}, {"speed": 134.0, "rpm": 6731.06, "engineLoad": 0.0, "coolantTemp": -32.0, "throttlePos": 44.71, "startTime": 1589252241.8317082, "steps": 16}, {"speed": 134.0, "rpm": 9173.98, "engineLoad": 0.0, "coolantTemp": -32.0, "throttlePos": 44.71, "startTime": 1589252245.8317244, "steps": 16}, {"speed": 134.0, "rpm": 10139.4, "engineLoad": 0.0, "coolantTemp": -32.0, "throttlePos": 44.71, "startTime": 1589252249.8298159, "steps": 16}, {"speed": 134.0, "rpm": 7510.25, "engineLoad": 0.0, "coolantTemp": 27.82, "throttlePos": 44.71, "startTime": 1589252253.832292, "steps": 16}, {"speed": 112.18, "rpm": 7510.25, "engineLoad": 0.0, "coolantTemp": 35.0, "throttlePos": 44.71, "startTime": 1589252257.835482, "steps": 16}, {"speed": 180.63, "rpm": 7510.25, "engineLoad": 0.0, "coolantTemp": 35.0, "throttlePos": 44.71, "startTime": 1589252261.8314586, "steps": 16}, {"speed": 162.32, "rpm": 7510.25, "engineLoad": 0.0, "coolantTemp": 35.0, "throttlePos": 44.71, "startTime": 1589252265.8311687, "steps": 16}, {"speed": 178.7, "rpm": 7510.25, "engineLoad": 0.0, "coolantTemp": 35.0, "throttlePos": 44.71, "startTime": 1589252269.8321316, "steps": 16}, {"speed": 228.0, "rpm": 7510.25, "engineLoad": 0.0, "coolantTemp": 35.0, "throttlePos": 44.71, "startTime": 1589252273.833418, "steps": 16}, {"speed": 228.0, "rpm": 7510.25, "engineLoad": 0.0, "coolantTemp": 35.0, "throttlePos": 44.71, "startTime": 1589252277.8311534, "steps": 16}]}, "30": {"startTime": "Tuesday May, 12 2020 05:59:09", "duration": 36.0, "avSpeed": 228.0, "avRPM": 13099.0, "avEngineLoad": 0.0, "avCoolantTemp": 35.0, "avThrottlePos": 27.52, "nSnaps": 9, "snaps": [{"speed": 228.0, "rpm": 7510.25, "engineLoad": 0.0, "coolantTemp": 35.0, "throttlePos": 44.71, "startTime": 1589252349.1436937, "steps": 10}, {"speed": 228.0, "rpm": 7510.25, "engineLoad": 0.0, "coolantTemp": 35.0, "throttlePos": 44.71, "startTime": 1589252353.1569672, "steps": 16}, {"speed": 228.0, "rpm": 7510.25, "engineLoad": 0.0, "coolantTemp": 35.0, "throttlePos": 44.71, "startTime": 1589252357.1486645, "steps": 16}, {"speed": 228.0, "rpm": 13441.44, "engineLoad": 0.0, "coolantTemp": 35.0, "throttlePos": 44.71, "startTime": 1589252361.1478114, "steps": 16}, {"speed": 228.0, "rpm": 16383.75, "engineLoad": 0.0, "coolantTemp": 35.0, "throttlePos": 29.73, "startTime": 1589252365.1500661, "steps": 16}, {"speed": 228.0, "rpm": 16383.75, "engineLoad": 0.0, "coolantTemp": 35.0, "throttlePos": 9.8, "startTime": 1589252369.1523535, "steps": 16}, {"speed": 228.0, "rpm": 16383.75, "engineLoad": 0.0, "coolantTemp": 35.0, "throttlePos": 9.8, "startTime": 1589252373.1495945, "steps": 13}, {"speed": 228.0, "rpm": 16383.75, "engineLoad": 0.0, "coolantTemp": 35.0, "throttlePos": 9.8, "startTime": 1589252378.9688728, "steps": 10}, {"speed": 228.0, "rpm": 16383.75, "engineLoad": 0.0, "coolantTemp": 35.0, "throttlePos": 9.8, "startTime": 1589252381.148284, "steps": 19}]}, "31": {"startTime": "Tuesday May, 12 2020 05:59:50", "duration": 40.0, "avSpeed": 128.85, "avRPM": 4808.0, "avEngineLoad": 4.01, "avCoolantTemp": 23.48, "avThrottlePos": 9.31, "nSnaps": 10, "snaps": [{"speed": 94.71, "rpm": 3211.9, "engineLoad": 40.16, "coolantTemp": 47.82, "throttlePos": 39.86, "startTime": 1589252390.7706077, "steps": 52}, {"speed": 228.0, "rpm": 13203.62, "engineLoad": 0.0, "coolantTemp": 35.0, "throttlePos": 9.8, "startTime": 1589252394.786812, "steps": 19}, {"speed": 228.0, "rpm": 7367.58, "engineLoad": 0.0, "coolantTemp": 35.0, "throttlePos": 9.8, "startTime": 1589252398.776007, "steps": 20}, {"speed": 228.0, "rpm": 6151.55, "engineLoad": 0.0, "coolantTemp": 35.0, "throttlePos": 9.8, "startTime": 1589252402.776461, "steps": 19}, {"speed": 228.0, "rpm": 9118.67, "engineLoad": 0.0, "coolantTemp": 35.0, "throttlePos": 9.8, "startTime": 1589252406.7757444, "steps": 19}, {"speed": 228.0, "rpm": 6743.25, "engineLoad": 0.0, "coolantTemp": 35.0, "throttlePos": 9.8, "startTime": 1589252410.7766573, "steps": 19}, {"speed": 47.39, "rpm": 1955.73, "engineLoad": 0.0, "coolantTemp": 11.09, "throttlePos": 3.46, "startTime": 1589252414.776249, "steps": 51}, {"speed": 6.55, "rpm": 329.77, "engineLoad": 0.0, "coolantTemp": 0.96, "throttlePos": 0.65, "startTime": 1589252418.7829945, "steps": 140}, {"speed": 0.0, "rpm": 0.0, "engineLoad": 0.0, "coolantTemp": 0.0, "throttlePos": 0.0, "startTime": 1589252422.7791064, "steps": 559}, {"speed": 0.0, "rpm": 0.0, "engineLoad": 0.0, "coolantTemp": 0.0, "throttlePos": 0.0, "startTime": 1589252426.785799, "steps": 99}]}, "32": {"startTime": "Tuesday May, 12 2020 06:00:31", "duration": 12.0, "avSpeed": 0.0, "avRPM": 0.0, "avEngineLoad": 0.0, "avCoolantTemp": 0.0, "avThrottlePos": 0.0, "nSnaps": 3, "snaps": [{"speed": 0.0, "rpm": 0.0, "engineLoad": 0.0, "coolantTemp": 0.0, "throttlePos": 0.0, "startTime": 1589252431.1265626, "steps": 99}, {"speed": 0.0, "rpm": 0.0, "engineLoad": 0.0, "coolantTemp": 0.0, "throttlePos": 0.0, "startTime": 1589252435.138401, "steps": 99}, {"speed": 0.0, "rpm": 0.0, "engineLoad": 0.0, "coolantTemp": 0.0, "throttlePos": 0.0, "startTime": 1589252439.130869, "steps": 99}]}, "33": {"startTime": "Tuesday May, 12 2020 06:00:44", "duration": 4.0, "avSpeed": 0.0, "avRPM": 0.0, "avEngineLoad": 0.0, "avCoolantTemp": 0.0, "avThrottlePos": 0.0, "nSnaps": 1, "snaps": [{"speed": 0.0, "rpm": 0.0, "engineLoad": 0.0, "coolantTemp": 0.0, "throttlePos": 0.0, "startTime": 1589252444.6101265, "steps": 99}]}, "34": {"startTime": "Tuesday May, 12 2020 06:00:54", "duration": 48.6, "avSpeed": 0.0, "avRPM": 0.0, "avEngineLoad": 0.0, "avCoolantTemp": 0.0, "avThrottlePos": 0.0, "nSnaps": 12, "snaps": [{"speed": 0.0, "rpm": 0.0, "engineLoad": 0.0, "coolantTemp": 0.0, "throttlePos": 0.0, "startTime": 1589252454.3266897, "steps": 77}, {"speed": 0.0, "rpm": 0.0, "engineLoad": 0.0, "coolantTemp": 0.0, "throttlePos": 0.0, "startTime": 1589252458.9024794, "steps": 3}, {"speed": 0.0, "rpm": 0.0, "engineLoad": 0.0, "coolantTemp": 0.0, "throttlePos": 0.0, "startTime": 1589252462.8982494, "steps": 3}, {"speed": 0.0, "rpm": 0.0, "engineLoad": 0.0, "coolantTemp": 0.0, "throttlePos": 0.0, "startTime": 1589252466.8988342, "steps": 3}, {"speed": 0.0, "rpm": 0.0, "engineLoad": 0.0, "coolantTemp": 0.0, "throttlePos": 0.0, "startTime": 1589252470.8983338, "steps": 4}, {"speed": 0.0, "rpm": 0.0, "engineLoad": 0.0, "coolantTemp": 0.0, "throttlePos": 0.0, "startTime": 1589252474.8981981, "steps": 3}, {"speed": 0.0, "rpm": 0.0, "engineLoad": 0.0, "coolantTemp": 0.0, "throttlePos": 0.0, "startTime": 1589252478.8977234, "steps": 3}, {"speed": 0.0, "rpm": 0.0, "engineLoad": 0.0, "coolantTemp": 0.0, "throttlePos": 0.0, "startTime": 1589252482.9003327, "steps": 3}, {"speed": 0.0, "rpm": 0.0, "engineLoad": 0.0, "coolantTemp": 0.0, "throttlePos": 0.0, "startTime": 1589252486.8986998, "steps": 3}, {"speed": 0.0, "rpm": 0.0, "engineLoad": 0.0, "coolantTemp": 0.0, "throttlePos": 0.0, "startTime": 1589252490.899493, "steps": 3}, {"speed": 0.0, "rpm": 0.0, "engineLoad": 0.0, "coolantTemp": 0.0, "throttlePos": 0.0, "startTime": 1589252494.898294, "steps": 3}, {"speed": 0.0, "rpm": 0.0, "engineLoad": 0.0, "coolantTemp": 0.0, "throttlePos": 0.0, "startTime": 1589252498.9005237, "steps": 3}]}, "35": {"startTime": "Tuesday May, 12 2020 06:02:10", "duration": 20.0, "avSpeed": 0.0, "avRPM": 0.0, "avEngineLoad": 0.0, "avCoolantTemp": 0.0, "avThrottlePos": 0.0, "nSnaps": 5, "snaps": [{"speed": 0.0, "rpm": 0.0, "engineLoad": 0.0, "coolantTemp": 0.0, "throttlePos": 0.0, "startTime": 1589252530.7750607, "steps": 88}, {"speed": 0.0, "rpm": 0.0, "engineLoad": 0.0, "coolantTemp": 0.0, "throttlePos": 0.0, "startTime": 1589252534.788167, "steps": 99}, {"speed": 0.0, "rpm": 0.0, "engineLoad": 0.0, "coolantTemp": 0.0, "throttlePos": 0.0, "startTime": 1589252538.7832017, "steps": 99}, {"speed": 0.0, "rpm": 0.0, "engineLoad": 0.0, "coolantTemp": 0.0, "throttlePos": 0.0, "startTime": 1589252542.782463, "steps": 100}, {"speed": 0.0, "rpm": 0.0, "engineLoad": 0.0, "coolantTemp": 0.0, "throttlePos": 0.0, "startTime": 1589252546.7822278, "steps": 99}]}, "36": {"startTime": "Tuesday May, 12 2020 06:03:37", "duration": 12.0, "avSpeed": 0.0, "avRPM": 0.0, "avEngineLoad": 0.0, "avCoolantTemp": 0.0, "avThrottlePos": 0.0, "nSnaps": 3, "snaps": [{"speed": 0.0, "rpm": 0.0, "engineLoad": 0.0, "coolantTemp": 0.0, "throttlePos": 0.0, "startTime": 1589252617.0275967, "steps": 90}, {"speed": 0.0, "rpm": 0.0, "engineLoad": 0.0, "coolantTemp": 0.0, "throttlePos": 0.0, "startTime": 1589252621.042362, "steps": 99}, {"speed": 0.0, "rpm": 0.0, "engineLoad": 0.0, "coolantTemp": 0.0, "throttlePos": 0.0, "startTime": 1589252625.0337236, "steps": 100}]}, "37": {"startTime": "Tuesday May, 12 2020 06:03:51", "duration": 32.0, "avSpeed": 36.75, "avRPM": 5625.0, "avEngineLoad": 0.0, "avCoolantTemp": 39.62, "avThrottlePos": 48.6, "nSnaps": 8, "snaps": [{"speed": 0.0, "rpm": 0.0, "engineLoad": 0.0, "coolantTemp": 0.0, "throttlePos": 0.0, "startTime": 1589252631.565555, "steps": 52}, {"speed": 0.0, "rpm": 7082.16, "engineLoad": 0.0, "coolantTemp": 0.0, "throttlePos": 0.0, "startTime": 1589252635.581186, "steps": 19}, {"speed": 0.0, "rpm": 7825.0, "engineLoad": 0.0, "coolantTemp": 20.63, "throttlePos": 64.01, "startTime": 1589252639.568389, "steps": 19}, {"speed": 30.11, "rpm": 7825.0, "engineLoad": 0.0, "coolantTemp": 90.0, "throttlePos": 100.0, "startTime": 1589252643.5690916, "steps": 19}, {"speed": 113.0, "rpm": 8269.03, "engineLoad": 0.0, "coolantTemp": 90.0, "throttlePos": 100.0, "startTime": 1589252647.5697274, "steps": 20}, {"speed": 113.0, "rpm": 10020.75, "engineLoad": 0.0, "coolantTemp": 90.0, "throttlePos": 100.0, "startTime": 1589252651.5697167, "steps": 18}, {"speed": 37.13, "rpm": 3982.39, "engineLoad": 0.0, "coolantTemp": 26.31, "throttlePos": 24.73, "startTime": 1589252655.568319, "steps": 51}, {"speed": 0.77, "rpm": 0.0, "engineLoad": 0.0, "coolantTemp": 0.0, "throttlePos": 0.0, "startTime": 1589252659.5688076, "steps": 601}]}, "38": {"startTime": "Tuesday May, 12 2020 06:04:44", "duration": 8.0, "avSpeed": 0.0, "avRPM": 0.0, "avEngineLoad": 0.0, "avCoolantTemp": 0.0, "avThrottlePos": 0.0, "nSnaps": 2, "snaps": [{"speed": 0.0, "rpm": 0.0, "engineLoad": 0.0, "coolantTemp": 0.0, "throttlePos": 0.0, "startTime": 1589252684.537443, "steps": 10}, {"speed": 0.0, "rpm": 0.0, "engineLoad": 0.0, "coolantTemp": 0.0, "throttlePos": 0.0, "startTime": 1589252688.5537145, "steps": 18}]}, "39": {"startTime": "Tuesday May, 12 2020 06:04:59", "duration": 24.0, "avSpeed": 0.0, "avRPM": 0.0, "avEngineLoad": 0.0, "avCoolantTemp": 0.0, "avThrottlePos": 0.0, "nSnaps": 6, "snaps": [{"speed": 0.0, "rpm": 0.0, "engineLoad": 0.0, "coolantTemp": 0.0, "throttlePos": 0.0, "startTime": 1589252699.7468688, "steps": 10}, {"speed": 0.0, "rpm": 0.0, "engineLoad": 0.0, "coolantTemp": 0.0, "throttlePos": 0.0, "startTime": 1589252703.7571714, "steps": 19}, {"speed": 0.0, "rpm": 0.0, "engineLoad": 0.0, "coolantTemp": 0.0, "throttlePos": 0.0, "startTime": 1589252707.7503464, "steps": 18}, {"speed": 0.0, "rpm": 0.0, "engineLoad": 0.0, "coolantTemp": 0.0, "throttlePos": 0.0, "startTime": 1589252711.747008, "steps": 19}, {"speed": 0.0, "rpm": 0.0, "engineLoad": 0.0, "coolantTemp": 0.0, "throttlePos": 0.0, "startTime": 1589252715.7453663, "steps": 19}, {"speed": 0.0, "rpm": 0.0, "engineLoad": 0.0, "coolantTemp": 0.0, "throttlePos": 0.0, "startTime": 1589252719.7445202, "steps": 19}]}, "40": {"startTime": "Tuesday May, 12 2020 06:06:45", "duration": 8.2, "avSpeed": 0.0, "avRPM": 0.0, "avEngineLoad": 0.0, "avCoolantTemp": 0.0, "avThrottlePos": 0.0, "nSnaps": 2, "snaps": [{"speed": 0, "rpm": 0, "engineLoad": 0, "coolantTemp": 0, "throttlePos": 0, "startTime": 1589252805.0540807, "steps": 0}, {"speed": 0, "rpm": 0, "engineLoad": 0, "coolantTemp": 0, "throttlePos": 0, "startTime": 1589252809.2392905, "steps": 0}]}, "41": {"startTime": "Tuesday May, 12 2020 06:07:09", "duration": 36.5, "avSpeed": 0.0, "avRPM": 0.0, "avEngineLoad": 0.0, "avCoolantTemp": 0.0, "avThrottlePos": 0.0, "nSnaps": 9, "snaps": [{"speed": 0, "rpm": 0, "engineLoad": 0, "coolantTemp": 0, "throttlePos": 0, "startTime": 1589252829.6192827, "steps": 0}, {"speed": 0, "rpm": 0, "engineLoad": 0, "coolantTemp": 0, "throttlePos": 0, "startTime": 1589252833.820994, "steps": 0}, {"speed": 0, "rpm": 0, "engineLoad": 0, "coolantTemp": 0, "throttlePos": 0, "startTime": 1589252837.7932136, "steps": 0}, {"speed": 0, "rpm": 0, "engineLoad": 0, "coolantTemp": 0, "throttlePos": 0, "startTime": 1589252841.818308, "steps": 0}, {"speed": 0, "rpm": 0, "engineLoad": 0, "coolantTemp": 0, "throttlePos": 0, "startTime": 1589252845.8077757, "steps": 0}, {"speed": 0, "rpm": 0, "engineLoad": 0, "coolantTemp": 0, "throttlePos": 0, "startTime": 1589252849.7991207, "steps": 0}, {"speed": 0, "rpm": 0, "engineLoad": 0, "coolantTemp": 0, "throttlePos": 0, "startTime": 1589252853.7961493, "steps": 0}, {"speed": 0, "rpm": 0, "engineLoad": 0, "coolantTemp": 0, "throttlePos": 0, "startTime": 1589252858.0839832, "steps": 0}, {"speed": 0, "rpm": 0, "engineLoad": 0, "coolantTemp": 0, "throttlePos": 0, "startTime": 1589252862.0874767, "steps": 0}]}, "42": {"startTime": "Tuesday May, 12 2020 06:07:50", "duration": 32.1, "avSpeed": 1.2, "avRPM": 2003.0, "avEngineLoad": 0.0, "avCoolantTemp": -0.34, "avThrottlePos": 0.13, "nSnaps": 8, "snaps": [{"speed": 0, "rpm": 0, "engineLoad": 0, "coolantTemp": 0, "throttlePos": 0, "startTime": 1589252870.7319875, "steps": 0}, {"speed": 0.0, "rpm": 0.0, "engineLoad": 0.0, "coolantTemp": 0.0, "throttlePos": 0.0, "startTime": 1589252874.9328966, "steps": 11}, {"speed": 0.0, "rpm": 520.24, "engineLoad": 0.0, "coolantTemp": 0.0, "throttlePos": 0.0, "startTime": 1589252878.7396123, "steps": 19}, {"speed": 0.0, "rpm": 1634.97, "engineLoad": 0.0, "coolantTemp": 0.0, "throttlePos": 0.0, "startTime": 1589252882.7395978, "steps": 19}, {"speed": 0.0, "rpm": 5430.6, "engineLoad": 0.0, "coolantTemp": 0.0, "throttlePos": 0.0, "startTime": 1589252886.7391415, "steps": 19}, {"speed": 0.0, "rpm": 4211.34, "engineLoad": 0.0, "coolantTemp": 0.0, "throttlePos": 0.0, "startTime": 1589252890.7359338, "steps": 19}, {"speed": 2.43, "rpm": 3797.97, "engineLoad": 0.0, "coolantTemp": -2.34, "throttlePos": 0.6, "startTime": 1589252894.7369223, "steps": 51}, {"speed": 7.16, "rpm": 425.4, "engineLoad": 0.0, "coolantTemp": -0.39, "throttlePos": 0.38, "startTime": 1589252898.7365475, "steps": 99}]}, "43": {"startTime": "Tuesday May, 12 2020 06:10:01", "duration": 44.8, "avSpeed": 0.51, "avRPM": 5673.0, "avEngineLoad": 0.0, "avCoolantTemp": 0.28, "avThrottlePos": 0.2, "nSnaps": 11, "snaps": [{"speed": 0, "rpm": 0, "engineLoad": 0, "coolantTemp": 0, "throttlePos": 0, "startTime": 1589253001.05751, "steps": 0}, {"speed": 0.0, "rpm": 0.0, "engineLoad": 0.0, "coolantTemp": 0.0, "throttlePos": 0.0, "startTime": 1589253005.256189, "steps": 11}, {"speed": 0.0, "rpm": 0.0, "engineLoad": 0.0, "coolantTemp": 0.0, "throttlePos": 0.0, "startTime": 1589253009.0617144, "steps": 19}, {"speed": 0.0, "rpm": 10917.68, "engineLoad": 0.0, "coolantTemp": 0.0, "throttlePos": 0.0, "startTime": 1589253013.0606835, "steps": 19}, {"speed": 0.0, "rpm": 9155.51, "engineLoad": 0.0, "coolantTemp": 0.0, "throttlePos": 0.0, "startTime": 1589253017.0647924, "steps": 19}, {"speed": 0.0, "rpm": 8624.27, "engineLoad": 0.0, "coolantTemp": 0.0, "throttlePos": 0.0, "startTime": 1589253021.0623317, "steps": 19}, {"speed": 0.0, "rpm": 6235.31, "engineLoad": 0.0, "coolantTemp": 0.0, "throttlePos": 0.0, "startTime": 1589253025.0643704, "steps": 19}, {"speed": 0.0, "rpm": 7104.54, "engineLoad": 0.0, "coolantTemp": 0.0, "throttlePos": 0.0, "startTime": 1589253029.0636492, "steps": 19}, {"speed": 0.0, "rpm": 8191.75, "engineLoad": 0.0, "coolantTemp": 0.0, "throttlePos": 0.0, "startTime": 1589253033.0624561, "steps": 23}, {"speed": 0.0, "rpm": 8191.75, "engineLoad": 0.0, "coolantTemp": 0.0, "throttlePos": 0.0, "startTime": 1589253037.8961582, "steps": 18}, {"speed": 5.56, "rpm": 3993.49, "engineLoad": 0.0, "coolantTemp": 3.13, "throttlePos": 2.18, "startTime": 1589253041.8972998, "steps": 30}]}, "44": {"startTime": "Tuesday May, 12 2020 06:12:49", "duration": 12.3, "avSpeed": 0.0, "avRPM": 0.0, "avEngineLoad": 0.0, "avCoolantTemp": 0.0, "avThrottlePos": 0.0, "nSnaps": 3, "snaps": [{"speed": 0, "rpm": 0, "engineLoad": 0, "coolantTemp": 0, "throttlePos": 0, "startTime": 1589253169.3382516, "steps": 0}, {"speed": 0, "rpm": 0, "engineLoad": 0, "coolantTemp": 0, "throttlePos": 0, "startTime": 1589253173.6543505, "steps": 0}, {"speed": 0, "rpm": 0, "engineLoad": 0, "coolantTemp": 0, "throttlePos": 0, "startTime": 1589253177.647442, "steps": 0}]}, "45": {"startTime": "Tuesday May, 12 2020 06:13:01", "duration": 8.0, "avSpeed": 35.1, "avRPM": 26.0, "avEngineLoad": 13.9, "avCoolantTemp": 19.86, "avThrottlePos": 11.0, "nSnaps": 2, "snaps": [{"speed": 70.2, "rpm": 52.86, "engineLoad": 27.8, "coolantTemp": 39.73, "throttlePos": 22.0, "startTime": 1589253181.8369036, "steps": 15}, {"speed": 0.0, "rpm": 0.0, "engineLoad": 0.0, "coolantTemp": 0.0, "throttlePos": 0.0, "startTime": 1589253185.854609, "steps": 15}]}, "46": {"startTime": "Tuesday May, 12 2020 06:13:13", "duration": 12.0, "avSpeed": 0.0, "avRPM": 0.0, "avEngineLoad": 0.0, "avCoolantTemp": 0.0, "avThrottlePos": 0.0, "nSnaps": 3, "snaps": [{"speed": 0.0, "rpm": 0.0, "engineLoad": 0.0, "coolantTemp": 0.0, "throttlePos": 0.0, "startTime": 1589253193.7811565, "steps": 16}, {"speed": 0.0, "rpm": 0.0, "engineLoad": 0.0, "coolantTemp": 0.0, "throttlePos": 0.0, "startTime": 1589253197.7993038, "steps": 15}, {"speed": 0.0, "rpm": 0.0, "engineLoad": 0.0, "coolantTemp": 0.0, "throttlePos": 0.0, "startTime": 1589253201.7903378, "steps": 15}]}, "47": {"startTime": "Tuesday May, 12 2020 06:13:27", "duration": 48.0, "avSpeed": 0.0, "avRPM": 5393.0, "avEngineLoad": 0.0, "avCoolantTemp": 0.0, "avThrottlePos": 0.0, "nSnaps": 12, "snaps": [{"speed": 0.0, "rpm": 0.0, "engineLoad": 0.0, "coolantTemp": 0.0, "throttlePos": 0.0, "startTime": 1589253207.7463064, "steps": 15}, {"speed": 0.0, "rpm": 0.0, "engineLoad": 0.0, "coolantTemp": 0.0, "throttlePos": 0.0, "startTime": 1589253211.759634, "steps": 15}, {"speed": 0.0, "rpm": 4013.48, "engineLoad": 0.0, "coolantTemp": 0.0, "throttlePos": 0.0, "startTime": 1589253215.7666018, "steps": 16}, {"speed": 0.0, "rpm": 7035.75, "engineLoad": 0.0, "coolantTemp": 0.0, "throttlePos": 0.0, "startTime": 1589253219.7508109, "steps": 16}, {"speed": 0.0, "rpm": 9534.7, "engineLoad": 0.0, "coolantTemp": 0.0, "throttlePos": 0.0, "startTime": 1589253223.7549996, "steps": 16}, {"speed": 0.0, "rpm": 11958.44, "engineLoad": 0.0, "coolantTemp": 0.0, "throttlePos": 0.0, "startTime": 1589253227.7541194, "steps": 16}, {"speed": 0.0, "rpm": 9294.34, "engineLoad": 0.0, "coolantTemp": 0.0, "throttlePos": 0.0, "startTime": 1589253231.7514737, "steps": 16}, {"speed": 0.0, "rpm": 5735.54, "engineLoad": 0.0, "coolantTemp": 0.0, "throttlePos": 0.0, "startTime": 1589253235.754438, "steps": 16}, {"speed": 0.0, "rpm": 3395.98, "engineLoad": 0.0, "coolantTemp": 0.0, "throttlePos": 0.0, "startTime": 1589253239.752716, "steps": 16}, {"speed": 0.0, "rpm": 4584.17, "engineLoad": 0.0, "coolantTemp": 0.0, "throttlePos": 0.0, "startTime": 1589253243.7512195, "steps": 16}, {"speed": 0.0, "rpm": 3724.11, "engineLoad": 0.0, "coolantTemp": 0.0, "throttlePos": 0.0, "startTime": 1589253247.753405, "steps": 16}, {"speed": 0.0, "rpm": 5436.16, "engineLoad": 0.0, "coolantTemp": 0.0, "throttlePos": 0.0, "startTime": 1589253251.7518914, "steps": 16}]}}}